{
	"next_post_id": 4,
	"next_comment_id": 9,
	"next_follow_id": 9,
	"avatar": "jpg",
	"user_name": "Pablo Arroyo",
	"hub": "1GrEenUGRWnzaNZjR3XsQa6dQgdPDTyt7i",
	"intro": "Tv and Radio student! ",
	"post": [
		{
			"post_id": 1,
			"date_added": 1474399545,
			"body": "Hello ZeroMe!"
		},
		{
			"post_id": 1474400148,
			"body": "Hello Everybody, I am from Argentina!",
			"date_added": 1474400146
		},
		{
			"post_id": 1474662353,
			"body": "I would like to know the reason you are using ZeroNet...and, How did you notice about it??",
			"date_added": 1474662350
		}
	],
	"post_like": {
		"1G22SgXJtdx9D6BfvXgjknD57Mi1wjnZX3_1": 1474399946,
		"17n6CSRU34hswqXDaTEDugQzN453UgGaND_1": 1474470873,
		"1GddA9Bb2ajk8SdejTV6Wvum2ku5V88bET_1474658459": 1474662294
	},
	"comment": [
		{
			"comment_id": 1,
			"body": "@Kopykate: Epale! jajaj yo tengo un amigo de Ecuador que me decía así ",
			"post_uri": "1G22SgXJtdx9D6BfvXgjknD57Mi1wjnZX3_1474400148",
			"date_added": 1474470669
		},
		{
			"comment_id": 2,
			"body": "@ulrichard: Nice! I am form the north of Argentina, Catamarca and Buenos Aires are very diferent...I really would like to go to Switzerland...how is it? ",
			"post_uri": "1G22SgXJtdx9D6BfvXgjknD57Mi1wjnZX3_1474400148",
			"date_added": 1474470722
		},
		{
			"comment_id": 3,
			"body": "hahaha, can we delete one hub?",
			"post_uri": "15Hi7MDddHwzTZmmcsj8MWLpZaDz6mLPXg_1",
			"date_added": 1474470893
		},
		{
			"comment_id": 4,
			"body": "@Anocisco: Hello Anocisco, where are you from?",
			"post_uri": "1G22SgXJtdx9D6BfvXgjknD57Mi1wjnZX3_1474400148",
			"date_added": 1474491658
		},
		{
			"comment_id": 5,
			"body": "@Kopykate: we can talk in spanish if you wish jajaja...it is sad to listen to very bad news from Venezuela.",
			"post_uri": "1G22SgXJtdx9D6BfvXgjknD57Mi1wjnZX3_1474400148",
			"date_added": 1474662198
		},
		{
			"comment_id": 6,
			"body": "@ks: Hi Ks, how are you? How is it in Denmark? It is far far away form here",
			"post_uri": "1G22SgXJtdx9D6BfvXgjknD57Mi1wjnZX3_1474400148",
			"date_added": 1474662237
		},
		{
			"comment_id": 7,
			"body": "@ulrichard: I cannot see you link :(",
			"post_uri": "1G22SgXJtdx9D6BfvXgjknD57Mi1wjnZX3_1474400148",
			"date_added": 1474662261
		},
		{
			"comment_id": 8,
			"body": "Hello sonicvisual! How are you? Where are you from?",
			"post_uri": "1GddA9Bb2ajk8SdejTV6Wvum2ku5V88bET_1474658459",
			"date_added": 1474662308
		}
	],
	"follow": [
		{
			"follow_id": 1,
			"hub": "1RedkCkVaXuVXrqCMpoXQS29bwaqsuFdL",
			"auth_address": "1DFDjUGJdSp1kMuFq1AtNS9ZWmkVtbp947",
			"user_name": "Mario",
			"date_added": 1474399556
		},
		{
			"follow_id": 2,
			"hub": "1RedkCkVaXuVXrqCMpoXQS29bwaqsuFdL",
			"auth_address": "1NZ4LvZqg61LxtRfEr5Y46KRhYCzWRnqck",
			"user_name": "Gallium",
			"date_added": 1474399986
		},
		{
			"follow_id": 3,
			"hub": "1RedkCkVaXuVXrqCMpoXQS29bwaqsuFdL",
			"auth_address": "16AFTG7vdicwJbRQpWc2F9BRHTE5MTftE7",
			"user_name": "Shift",
			"date_added": 1474400067
		},
		{
			"follow_id": 4,
			"hub": "1GrEenUGRWnzaNZjR3XsQa6dQgdPDTyt7i",
			"auth_address": "17tpqoZw9eG2MQq6C3CVZ9MVxJxLTtCPZC",
			"user_name": "0face",
			"date_added": 1474400168
		},
		{
			"follow_id": 5,
			"hub": "1GrEenUGRWnzaNZjR3XsQa6dQgdPDTyt7i",
			"auth_address": "19uWzxhn3oD5vKcNLhSa3GYcZkQQiTNnLv",
			"user_name": "Linuksiarz",
			"date_added": 1474662284
		},
		{
			"follow_id": 6,
			"hub": "1GrEenUGRWnzaNZjR3XsQa6dQgdPDTyt7i",
			"auth_address": "1GddA9Bb2ajk8SdejTV6Wvum2ku5V88bET",
			"user_name": "Sonicvisual",
			"date_added": 1474662285
		},
		{
			"follow_id": 7,
			"hub": "1RedkCkVaXuVXrqCMpoXQS29bwaqsuFdL",
			"auth_address": "1NAaF8VitwKSPo79RzJFhqz14gndmdWcGV",
			"user_name": "Mynameislegion",
			"date_added": 1474682461
		},
		{
			"follow_id": 8,
			"hub": "1BLueGvui1GdbtsjcKqCf4F67uKfritG49",
			"auth_address": "1H9R6W9QWUpYiJkLyAsFXmXhAV7HEqoHtN",
			"user_name": "Flyman",
			"date_added": 1474682494
		}
	]
}