{
	"next_post_id": 3,
	"next_comment_id": 1,
	"next_follow_id": 2,
	"avatar": "jpg",
	"user_name": "Kenchoh",
	"hub": "1BLueGvui1GdbtsjcKqCf4F67uKfritG49",
	"intro": "新 ZeroNet 用户",
	"post": [
		{
			"post_id": 1,
			"date_added": 1479618144,
			"body": "你好 ZeroMe!"
		},
		{
			"post_id": 1479618287,
			"body": "如果Twitter挂了那我就用这个好了",
			"date_added": 1479618285
		}
	],
	"post_like": {},
	"comment": [],
	"follow": [
		{
			"follow_id": 1,
			"hub": "1RedkCkVaXuVXrqCMpoXQS29bwaqsuFdL",
			"auth_address": "13Z7XxTa7JuFat3KzzMWu3onwM6biLuurJ",
			"user_name": "P2P",
			"date_added": 1479618317
		}
	]
}