{
	"next_post_id": 2,
	"next_comment_id": 5,
	"next_follow_id": 1,
	"avatar": "generate",
	"user_name": "Tempid",
	"hub": "1GrEenUGRWnzaNZjR3XsQa6dQgdPDTyt7i",
	"intro": "Random ZeroNet user",
	"post": [
		{
			"post_id": 1,
			"date_added": 1478188072,
			"body": "Hello ZeroMe!"
		}
	],
	"post_like": {},
	"comment": [
		{
			"comment_id": 1,
			"body": "@P2P: 所以，是他自己没坚守，而不是方法有问题。为了革命/民族/国家利益抛头颅洒热血的前辈又有多少？林则徐的**苟利国家生死以，岂因祸福避趋之**又是在一种什么样的思想和心态下写的？文天祥从容取义，宁死不屈的精神岂非中华民族的风骨写照？现代思想文化正处于断层，更多的是空虚而非正义。人不知耻百事可行嘛，。最终的问题只在于思想，而非其他。",
			"post_uri": "1FHN4oukAG7zFUpiC9L2iz7QpQVTuT3xkz_1478179494",
			"date_added": 1478188120
		},
		{
			"comment_id": 2,
			"body": "民无正心，心无定性，最终被反派官员离间，呵呵，怪得了谁。",
			"post_uri": "1FHN4oukAG7zFUpiC9L2iz7QpQVTuT3xkz_1478179494",
			"date_added": 1478188643
		},
		{
			"comment_id": 3,
			"body": "@Mzero: 若是有坚定不移的世界观，自然不可能不停的被塑造。",
			"post_uri": "1FHN4oukAG7zFUpiC9L2iz7QpQVTuT3xkz_1478179494",
			"date_added": 1478189285
		},
		{
			"comment_id": 4,
			"body": "子曰：择其善者而从之，其不善者而改之，这是在有基础的条件下进行的，而非普通人一上手就是，否则只能是邯郸学步，捡芝麻丢西瓜最终小猫钓鱼。因此，一个稳固的基石，正确的三观，对人们来说特别重要。",
			"post_uri": "1FHN4oukAG7zFUpiC9L2iz7QpQVTuT3xkz_1478179494",
			"date_added": 1478189671
		}
	],
	"follow": []
}