{
	"next_post_id": 3,
	"next_comment_id": 1,
	"next_follow_id": 9,
	"avatar": "generate",
	"user_name": "Antifa",
	"hub": "1RedkCkVaXuVXrqCMpoXQS29bwaqsuFdL",
	"intro": "Random ZeroNet user",
	"post": [
		{
			"post_id": 1,
			"date_added": 1474908414,
			"body": "Hello ZeroMe!"
		},
		{
			"post_id": 1474908431,
			"body": "Smash the State!",
			"date_added": 1474908429
		}
	],
	"post_like": {},
	"comment": [],
	"follow": [
		{
			"follow_id": 1,
			"hub": "1RedkCkVaXuVXrqCMpoXQS29bwaqsuFdL",
			"auth_address": "1L1aeW5p3tvk19vFj62WbZ5fvo3C7D9zw2",
			"user_name": "Fiveeleven",
			"date_added": 1474909268
		},
		{
			"follow_id": 2,
			"hub": "1GrEenUGRWnzaNZjR3XsQa6dQgdPDTyt7i",
			"auth_address": "19uWzxhn3oD5vKcNLhSa3GYcZkQQiTNnLv",
			"user_name": "Linuksiarz",
			"date_added": 1474909274
		},
		{
			"follow_id": 3,
			"hub": "1GrEenUGRWnzaNZjR3XsQa6dQgdPDTyt7i",
			"auth_address": "1BYUHmqCj8FD5MADQtE9NEVAnqNbyyiEam",
			"user_name": "Entropy",
			"date_added": 1474909284
		},
		{
			"follow_id": 4,
			"hub": "1GrEenUGRWnzaNZjR3XsQa6dQgdPDTyt7i",
			"auth_address": "1A3XsuLB6P7LQPCw1QWASG7RGSwrCv6Xib",
			"user_name": "Elspru",
			"date_added": 1474909287
		},
		{
			"follow_id": 5,
			"hub": "1D7xb8vwnWUYSXziENcnoi3meD5Gk2xgFj",
			"auth_address": "16dVbybDseQBQnxdJDuQhCzYAij8iR8YEc",
			"user_name": "Heathenman",
			"date_added": 1474909293
		},
		{
			"follow_id": 6,
			"hub": "1GrEenUGRWnzaNZjR3XsQa6dQgdPDTyt7i",
			"auth_address": "16w7UuJAHbt8YBa8zxHS7UFk9mq8Q5DpE4",
			"user_name": "Kopykate",
			"date_added": 1474909296
		},
		{
			"follow_id": 7,
			"hub": "1GrEenUGRWnzaNZjR3XsQa6dQgdPDTyt7i",
			"auth_address": "17tpqoZw9eG2MQq6C3CVZ9MVxJxLTtCPZC",
			"user_name": "0face",
			"date_added": 1474909302
		},
		{
			"follow_id": 8,
			"hub": "1GrEenUGRWnzaNZjR3XsQa6dQgdPDTyt7i",
			"auth_address": "1G22SgXJtdx9D6BfvXgjknD57Mi1wjnZX3",
			"user_name": "Pablo Arroyo",
			"date_added": 1474909307
		}
	]
}