{
	"next_comment_id": 4,
	"user_name": "Border0464fred",
	"hub": "1BLueGvui1GdbtsjcKqCf4F67uKfritG49",
	"post_like": {},
	"comment": [
		{
			"comment_id": 1,
			"body": "Reproductive build is the answer to this but it imply open source and independent review. ",
			"post_uri": "1PSaHi14Xh4Kjo3yyjDgbRtj4YLQgWV4QJ_1480514467",
			"date_added": 1480515344
		},
		{
			"comment_id": 2,
			"body": "ahhhh! plzzzz I try to keep a bit of hope :p \n\n",
			"post_uri": "1PSaHi14Xh4Kjo3yyjDgbRtj4YLQgWV4QJ_1480514467",
			"date_added": 1480518397
		},
		{
			"comment_id": 3,
			"body": "we are doomed, we are fucking doomed",
			"post_uri": "1PSaHi14Xh4Kjo3yyjDgbRtj4YLQgWV4QJ_1480514467",
			"date_added": 1480518419
		}
	],
	"flags": {},
	"comment_like": {}
}