{
	"next_post_id": 4,
	"next_comment_id": 7,
	"next_follow_id": 7,
	"avatar": "png",
	"user_name": "P0rt4v0x",
	"hub": "1GrEenUGRWnzaNZjR3XsQa6dQgdPDTyt7i",
	"intro": "Blog: http://127.0.0.1:43110/1J2vP4zfjufxmHWGFgobQsj3ARUFPPVW5C/\n\nAyudando a proteger tu seguridad y privacidad en Internet.\n\nPublicando en espanol e ingles.",
	"post": [
		{
			"post_id": 1,
			"date_added": 1478327606,
			"body": "Hello ZeroMe!"
		},
		{
			"post_id": 1478327777,
			"body": "ayudando a la comunidad con su seguridad y privacidad",
			"date_added": 1478327775
		},
		{
			"post_id": 1478400390,
			"body": "pronto a publicar un blog para ayudarte con tu seguridad informatica y privacidad en la web",
			"date_added": 1478400387
		}
	],
	"post_like": {},
	"comment": [
		{
			"comment_id": 1,
			"body": "Totally agree with that, we all have the right to speak and express our opinions. As a P2P network the content we publish should be respected. And if there is something that \"should not be there\" then people shouldnt seed it.",
			"post_uri": "15Zmh5dcKYDxo3mUFTXwJPUHAbczeafAUp_1478410096",
			"date_added": 1478412716
		},
		{
			"comment_id": 2,
			"body": "hello!",
			"post_uri": "15ZZxswmiYYttViTJVWp8kWEzR3vFKe5Ha_1",
			"date_added": 1478414087
		},
		{
			"comment_id": 3,
			"body": "hello!",
			"post_uri": "16XF39wYX5kqWdeKsaPUq9pgJjpPhBNm7m_1",
			"date_added": 1478414206
		},
		{
			"comment_id": 4,
			"body": "hello!",
			"post_uri": "1Gvt9G2jNzDgwonTai9phqpJXsE8qpHmQq_1",
			"date_added": 1478414229
		},
		{
			"comment_id": 5,
			"body": "hello...",
			"post_uri": "1Hs6FJ3tpmqz5NbcbqeTzN457cdYr6Z6EX_1",
			"date_added": 1478414242
		},
		{
			"comment_id": 6,
			"body": "hello!",
			"post_uri": "1AnkqDxPyZv6XMtBnfFdwgrvjPM3xkF9D6_1",
			"date_added": 1478414247
		}
	],
	"follow": [
		{
			"follow_id": 1,
			"hub": "1GrEenUGRWnzaNZjR3XsQa6dQgdPDTyt7i",
			"auth_address": "1Cj94xYhjEj8jrk3c94V8s1QzpzVksGYBd",
			"user_name": "P0rt4v0x",
			"date_added": 1478327638
		},
		{
			"follow_id": 2,
			"hub": "1GrEenUGRWnzaNZjR3XsQa6dQgdPDTyt7i",
			"auth_address": "15Zmh5dcKYDxo3mUFTXwJPUHAbczeafAUp",
			"user_name": "HelloArch",
			"date_added": 1478412991
		},
		{
			"follow_id": 3,
			"hub": "1RedkCkVaXuVXrqCMpoXQS29bwaqsuFdL",
			"auth_address": "1958F7oCppj78MP966AfojMQwHg2WUupzq",
			"user_name": "Lmath",
			"date_added": 1478413051
		},
		{
			"follow_id": 4,
			"hub": "1BLueGvui1GdbtsjcKqCf4F67uKfritG49",
			"auth_address": "18hidquEH7k6Dnn5MDd4zJFJ2cTUF22wk2",
			"user_name": "Cxgreat2014",
			"date_added": 1478413661
		},
		{
			"follow_id": 5,
			"hub": "1GrEenUGRWnzaNZjR3XsQa6dQgdPDTyt7i",
			"auth_address": "1FHN4oukAG7zFUpiC9L2iz7QpQVTuT3xkz",
			"user_name": "猫叉酱",
			"date_added": 1478414029
		},
		{
			"follow_id": 6,
			"hub": "1GrEenUGRWnzaNZjR3XsQa6dQgdPDTyt7i",
			"auth_address": "1EFRUQjydLVFKNFBiF2LW5rpQeqEr8EA6M",
			"user_name": "Rainlime",
			"date_added": 1478414185
		}
	]
}