{
	"next_post_id": 11,
	"next_comment_id": 9,
	"next_follow_id": 1,
	"avatar": "png",
	"user_name": "INXIAN",
	"hub": "1RedkCkVaXuVXrqCMpoXQS29bwaqsuFdL",
	"intro": "INXIAN, Made in Xian, www.inxian.com",
	"post": [
		{
			"post_id": 1,
			"date_added": 1470995926,
			"body": "大家好，我来自西安。Hello, This is Xian, China."
		},
		{
			"post_id": 2,
			"body": "[活动预告] 韩国驻西安总领事馆将于8月15日（星期一）上午10点在长安区杜曲镇光复军第二支队标识石纪念公园举行8·15光复节纪念活动。\n\n光复军是二战期间韩国在华流亡政府的军队，由在华朝鲜人组成。1940年9月17日成立于重庆，1942年9月迁往西安。兵力最多高达5万人，曾和中国人一起参加了抗日战争。1946年，光复军返韩。",
			"date_added": 1470996660
		},
		{
			"post_id": 3,
			"body": "[软件更新] 大支那局域网( GFW )内最强的翻墙工具 shadowsocks 在8月13日晚间推出了 3.2 版的 Windows 客户端，增加了不少有趣的性能！欢迎各位下载、体验：https://github.com/shadowsocks/shadowsocks-windows/releases/tag/3.2",
			"date_added": 1471141575
		},
		{
			"post_id": 5,
			"body": "[用外包的形式变相裁员] 西安圣象木业有限公司工程部的约70名安装工人，被西安圣象外包给了第三方公司，引发员工维权。西安圣象人事部表示：是工人自愿离职并入职到了第三方承包公司，这些自愿离职都是发生在将工程部外包给第三方公司之后。\n\n点评：业务外包属于资产剥离，人员属于资产的一部分。在整个市场环境都疲软的情况下，西安圣象木业有限公司将工程部外包的做法其实是间接裁减人员。",
			"date_added": 1471143518
		},
		{
			"post_id": 6,
			"body": "[敬酒不吃要你命！] 渭南邢某给初次见面的贾某某敬酒被拒，觉得很没面子，遂与对方发生冲突，打斗中，邢某被贾某某用随身携带的刀具刺伤，经抢救无效身亡。8月11日，渭南市中级人民法院审理了此案。庭审中，被害人邢某的家属提起附带民事诉讼，贾某某对所犯罪行供认不讳，并向死者家属鞠躬道歉。法庭将择日宣判。\n\n点评：陕西这个地方酒疯子很多，敬酒、劝酒的风俗更不好，一言不合就动刀，因喝酒每年都死不少人。",
			"date_added": 1471144470
		},
		{
			"post_id": 7,
			"body": "[秦凯宣布退役，将和何姿结婚] 结束了里约奥运会之后，秦凯正式对外宣布退役。秦凯参加了3届奥运会，获得2金1银2铜，这是陕西籍运动员在奥运会上取得的最好成绩。\n\n四年前伦敦奥运时，秦凯在跳水男子三米板项目错失金牌，何姿上前拥抱住痛哭的秦凯让两人的秘密恋情随之曝光。而此次两人又携手前往里约为中国军团出战，此前秦凯还在社交媒体上大方秀出了他和何姿的合影，并笑侃二人是“西红柿炒蛋”组合，这对跳水界的“金童玉女”也许好事将近。",
			"date_added": 1471146211
		},
		{
			"post_id": 1473233960,
			"body": "[公告] 9月8日9点，杜某刚一案将在西安中级法院(辛家庙西村附近)第27法庭开庭。INXIAN 将在第一时间告知大家庭审情况。当天是工作日，若有拨冗前来旁听者，请携带好身份证原件。此案是因杜某刚长期盗用 INXIAN 的 IP 进行商业活动而引发的。在此次开庭之前，因杜某刚提出管辖权异议而转至中级法院。",
			"date_added": 1473233952
		},
		{
			"post_id": 1473412011,
			"body": "[庭审简报] 9月8日当天，杜某刚未出庭，他委派了两名律师。开庭后，他的两名律师拒不承认杜某刚是账号为 zaixian6688 的冒牌「在西安」的持有人、运营者和受益者。但是，所有的证据都指向了杜某刚。然而，碑林法院转给西安中级法院的案卷中竟然没有腾讯公司提供的一份关键证据！(简报全文 http://127.0.0.1:43110/inxian.bit/?Post:156 )",
			"date_added": 1473412002
		},
		{
			"post_id": 1478416951,
			"body": "2015年2月，INXIAN 旗下「在西安、IN直播」两个微博账户被封之后，孔伟（悦西安网）疯狂造谣、污蔑、攻击、抹黑。鉴于此人的恶劣行为，INXIAN 提出了严肃的法律诉讼，日前，此案宣判，孔伟败诉，而且没有上诉。http://127.0.0.1:43110/inxian.bit/?Post:157",
			"date_added": 1478416941
		}
	],
	"post_like": {
		"13bt9n8uszaJuDD3RKxYU1fJMF36G3dK1U_1": 1470996112
	},
	"comment": [
		{
			"comment_id": 1,
			"body": "@这人笑起来很Cute: 嗯！谢谢鼓励！INXIAN 一直都是乐于开发新天地的。",
			"post_uri": "13bt9n8uszaJuDD3RKxYU1fJMF36G3dK1U_2",
			"date_added": 1471141337
		},
		{
			"comment_id": 2,
			"body": "@Jayofthezero: Yes,Thanks for the suggestion.",
			"post_uri": "13bt9n8uszaJuDD3RKxYU1fJMF36G3dK1U_7",
			"date_added": 1471157950
		},
		{
			"comment_id": 3,
			"body": "@R3df0x: 哈哈！看来是长期关注我们的老朋友啦！",
			"post_uri": "13bt9n8uszaJuDD3RKxYU1fJMF36G3dK1U_7",
			"date_added": 1473232399
		},
		{
			"comment_id": 4,
			"body": "@Cxgreat2014: 最近我们一直在思考用什么更好、更有趣的方式来做「内容」。",
			"post_uri": "13bt9n8uszaJuDD3RKxYU1fJMF36G3dK1U_7",
			"date_added": 1473232427
		},
		{
			"comment_id": 5,
			"body": "谢谢提醒，已升级。",
			"post_uri": "13Z7XxTa7JuFat3KzzMWu3onwM6biLuurJ_1473143437",
			"date_added": 1473233802
		},
		{
			"comment_id": 6,
			"body": "@P2P: 此处的 IP 是指 智慧财产权 (Intellectual Property)，详情请浏览：http://media.weibo.cn/article?id=2309403937836230402240",
			"post_uri": "13bt9n8uszaJuDD3RKxYU1fJMF36G3dK1U_1473233960",
			"date_added": 1473379687
		},
		{
			"comment_id": 7,
			"body": "这个不是问题。主要是内容的观赏性和可读性。",
			"post_uri": "14HCuNUPNauHjToiDN4fQjedc5JPoQdciY_1473718715",
			"date_added": 1473754792
		},
		{
			"comment_id": 8,
			"body": "@Bingyuhuo: 比五毛还要愚蠢的一种东西：自干五。",
			"post_uri": "13bt9n8uszaJuDD3RKxYU1fJMF36G3dK1U_1478416951",
			"date_added": 1479709997
		}
	],
	"follow": []
}