{
	"next_post_id": 3,
	"next_comment_id": 3,
	"next_follow_id": 5,
	"avatar": "generate",
	"user_name": "Stillwarter",
	"hub": "1GrEenUGRWnzaNZjR3XsQa6dQgdPDTyt7i",
	"intro": "Random ZeroNet user",
	"post": [
		{
			"post_id": 1,
			"date_added": 1472308050,
			"body": "Hello ZeroMe!"
		},
		{
			"post_id": 1472308078,
			"body": "a new world",
			"date_added": 1472308076
		}
	],
	"post_like": {
		"1FVwrkrpwe2DPu6Q4qpPRks2aAfRQ43DEC_1": 1472308303,
		"1FVwrkrpwe2DPu6Q4qpPRks2aAfRQ43DEC_1472302437": 1472308328
	},
	"comment": [
		{
			"comment_id": 1,
			"body": "doesn't is？",
			"post_uri": "19pG5guxaZFWiUotZrwqVdCW7TomPV9kcZ_1472308078",
			"date_added": 1472308097
		},
		{
			"comment_id": 2,
			"body": "@Stillwarter: yeah！",
			"post_uri": "19pG5guxaZFWiUotZrwqVdCW7TomPV9kcZ_1472308078",
			"date_added": 1472308107
		}
	],
	"follow": [
		{
			"follow_id": 1,
			"hub": "1GrEenUGRWnzaNZjR3XsQa6dQgdPDTyt7i",
			"auth_address": "19pG5guxaZFWiUotZrwqVdCW7TomPV9kcZ",
			"user_name": "Stillwarter",
			"date_added": 1472308255
		},
		{
			"follow_id": 2,
			"hub": "1GrEenUGRWnzaNZjR3XsQa6dQgdPDTyt7i",
			"auth_address": "164webMv4AhyZVcYskkrUAHGJTRTTzBqn2",
			"user_name": "Haflover",
			"date_added": 1472308271
		},
		{
			"follow_id": 3,
			"hub": "1GrEenUGRWnzaNZjR3XsQa6dQgdPDTyt7i",
			"auth_address": "115P86wFikGndN32MSyjh4svy8Tq6PuKyK",
			"user_name": "Pd",
			"date_added": 1472308275
		},
		{
			"follow_id": 4,
			"hub": "1GrEenUGRWnzaNZjR3XsQa6dQgdPDTyt7i",
			"auth_address": "1FVwrkrpwe2DPu6Q4qpPRks2aAfRQ43DEC",
			"user_name": "Bloxx",
			"date_added": 1472308283
		}
	]
}