{
	"next_post_id": 3,
	"next_comment_id": 5,
	"next_follow_id": 2,
	"avatar": "generate",
	"user_name": "Renha",
	"hub": "1BLueGvui1GdbtsjcKqCf4F67uKfritG49",
	"intro": "Random ZeroNet user",
	"post": [
		{
			"post_id": 1,
			"date_added": 1475495204,
			"body": "Hello ZeroMe!"
		},
		{
			"post_id": 1475496066,
			"body": "Whoa, looks like ZeroMe is good enough alternative to juick.com, we just need to move some users",
			"date_added": 1475496064
		}
	],
	"post_like": {
		"1PniNzyi8fygvwyBaLpA9oBDVWZ5fXuJUw_1475393382": 1475495239,
		"1PniNzyi8fygvwyBaLpA9oBDVWZ5fXuJUw_1475474775": 1475501169,
		"1BYU9zV786auJ29dF3HMAQYhxA2WgN4ofi_1475519556": 1475566006,
		"1PniNzyi8fygvwyBaLpA9oBDVWZ5fXuJUw_1475766922": 1476094586,
		"1PniNzyi8fygvwyBaLpA9oBDVWZ5fXuJUw_1475658002": 1476094595
	},
	"comment": [
		{
			"comment_id": 1,
			"body": "Да, к сожалению анонимность нивелирует влияние общества на становление личности, а так как в отсутствии общества полноценной личности нет - нет её и у людей, воспитанных дикими имиджбордами.",
			"post_uri": "1PniNzyi8fygvwyBaLpA9oBDVWZ5fXuJUw_1475474775",
			"date_added": 1475501274
		},
		{
			"comment_id": 2,
			"body": "а что за ссылка \"Кросспостинг\"? У меня оная ведёт на домашнюю страницу ZeroMe+.",
			"post_uri": "1PniNzyi8fygvwyBaLpA9oBDVWZ5fXuJUw_1475474775",
			"date_added": 1475501336
		},
		{
			"comment_id": 3,
			"body": "@Zerro: ну сейчас с регистрацией относительно норм, жаббер/соцсети",
			"post_uri": "1BidCEzNjETypKRCaRFQ6myvDo71o6FDyC_1475496066",
			"date_added": 1475565948
		},
		{
			"comment_id": 4,
			"body": "@Balancer73: > приятная фишка после juick (или Twitter) — возможность редактировать свои сообщения. - зато неприятная фишка - другие могут редактировать свои сообщения",
			"post_uri": "1PniNzyi8fygvwyBaLpA9oBDVWZ5fXuJUw_1476201962",
			"date_added": 1476711819
		}
	],
	"follow": [
		{
			"follow_id": 1,
			"hub": "1BLueGvui1GdbtsjcKqCf4F67uKfritG49",
			"auth_address": "1PniNzyi8fygvwyBaLpA9oBDVWZ5fXuJUw",
			"user_name": "Balancer73",
			"date_added": 1475495226
		}
	]
}